Metadata-Version: 1.2
Name: sorting-package
Version: 1
Summary: Fast sorting module
Home-page: https://github.com/the-gigi/conman
Author: Fongrad Anastasia
Author-email: fongradnastya@gmail.com
License: MIT
Platform: UNKNOWN
Requires-Python: >=3.6, <4
